myconf/__init__.py
myconf-1.1.2.dist-info/LICENSE
myconf-1.1.2.dist-info/METADATA
myconf-1.1.2.dist-info/WHEEL
myconf-1.1.2.dist-info/top_level.txt
myconf-1.1.2.dist-info/RECORD
