Metadata-Version: 2.1
Name: myconf
Version: 1.1.2
Summary: load json or yaml files as python dict, auto refresh when file changing, support item changing callback
Home-page: https://github.com/thuhak/myconf
Author: thuhak
Author-email: thuhak.zhou@nio.com
License: UNKNOWN
Keywords: configfile
Platform: UNKNOWN
Requires-Dist: PyYAML (>=3.13)
Requires-Dist: jmespath (>=0.9.3)
